adafruit_aw9523.py
adafruit_circuitpython_aw9523-1.1.14.dist-info/licenses/LICENSE
adafruit_circuitpython_aw9523-1.1.14.dist-info/METADATA
adafruit_circuitpython_aw9523-1.1.14.dist-info/WHEEL
adafruit_circuitpython_aw9523-1.1.14.dist-info/top_level.txt
adafruit_circuitpython_aw9523-1.1.14.dist-info/RECORD
