Metadata-Version: 2.4
Name: adafruit-circuitpython-aw9523
Version: 1.1.14
Summary: Python library for AW9523 GPIO expander and LED driver
Author-email: Adafruit Industries <circuitpython@adafruit.com>
License: MIT
Project-URL: Homepage, https://github.com/adafruit/Adafruit_CircuitPython_AW9523
Keywords: adafruit,blinka,circuitpython,micropython,aw9523,gpio,expander,led,constant-,current,i2c
Classifier: Intended Audience :: Developers
Classifier: Topic :: Software Development :: Libraries
Classifier: Topic :: Software Development :: Embedded Systems
Classifier: Topic :: System :: Hardware
Classifier: License :: OSI Approved :: MIT License
Classifier: Programming Language :: Python :: 3
License-File: LICENSE
Requires-Dist: Adafruit-Blinka
Requires-Dist: adafruit-circuitpython-register
Requires-Dist: adafruit-circuitpython-busdevice
Provides-Extra: optional
Dynamic: license-file
